{
    "110_up": [],
    "110_down": [],
    "157_up": [],
    "157_down": [],
    "1341_up": [],
    "1341_down": [],
    "2349_up": [],
    "2349_down": [],
    "8_up": [],
    "8_down": [],
    "1128_up": [],
    "1128_down": [],
    "1838_up": [],
    "1838_down": [],
    "229_up": [],
    "229_down": [],
    "506_up": [],
    "506_down": [],
    "5071_up": [],
    "5071_down": [],
    "6030_up": [],
    "6030_down": [],
    "5002_up": [],
    "5002_down": [],
    "6246_up": [],
    "6246_down": [],
    "260_up": [],
    "260_down": [],
    "873_up": [],
    "873_down": [],
    "117_up": [],
    "117_down": [],
    "5027_up": [],
    "5027_down": [],
    "860_up": [],
    "860_down": [],
    "712_up": [],
    "712_down": [],
    "318_up": [],
    "318_down": [],
    "6237_up": [],
    "6237_down": [],
    "872_up": [],
    "872_down": [],
    "K210_up": [],
    "K210_down": [],
    "851_up": [],
    "851_down": [],
    "2017_up": [],
    "2017_down": [],
    "179_up": [],
    "179_down": [],
    "6225_up": [],
    "6225_down": [],
    "813_up": [],
    "813_down": [],
    "322_up": [],
    "322_down": [],
    "152_up": [],
    "152_down": [],
    "616_up": [],
    "616_down": [],
    "6144_up": [],
    "6144_down": [],
    "802_up": [],
    "802_down": [],
    "6211_up": [],
    "6211_down": [],
    "2518_up": [],
    "2518_down": [],
    "511_up": [],
    "511_down": [],
    "541_up": [],
    "541_down": [],
    "569_up": [],
    "569_down": [],
    "13_up": [],
    "13_down": [],
    "1867_up": [],
    "1867_down": [],
    "1836_up": [],
    "1836_down": [],
    "529_up": [],
    "529_down": [],
    "867_up": [],
    "867_down": [],
    "2866_up": [],
    "2866_down": [],
    "824_up": [],
    "824_down": [],
    "1316_up": [],
    "1316_down": [],
    "6247_up": [],
    "6247_down": [],
    "6145_up": [],
    "6145_down": [],
    "1340_up": [],
    "1340_down": [],
    "226_up": [],
    "226_down": [],
    "711_up": [],
    "711_down": [],
    "723_up": [],
    "723_down": [],
    "866_up": [],
    "866_down": [],
    "333_up": [],
    "333_down": [],
    "884_up": [],
    "884_down": [],
    "25_up": [],
    "25_down": [],
    "5072_up": [],
    "5072_down": [],
    "6214_up": [],
    "6214_down": [],
    "2319_up": [],
    "2319_down": [],
    "812_up": [],
    "812_down": [],
    "865_up": [],
    "865_down": [],
    "5026_up": [],
    "5026_down": [],
    "213_up": [],
    "213_down": [],
    "1123_up": [],
    "1123_down": [],
    "831_up": [],
    "831_down": [],
    "5064_up": [],
    "5064_down": [],
    "2341_up": [],
    "2341_down": [],
    "2350_up": [],
    "2350_down": [],
    "253_up": [],
    "253_down": [],
    "890_up": [],
    "890_down": [],
    "6045_up": [],
    "6045_down": [],
    "2302_up": [],
    "2302_down": [],
    "2179_up": [],
    "2179_down": [],
    "202_up": [],
    "202_down": [],
    "6027_up": [],
    "6027_down": [],
    "6238_up": [],
    "6238_down": [],
    "128_up": [],
    "128_down": [],
    "803_up": [],
    "803_down": [],
    "218_up": [],
    "218_down": [],
    "1336_up": [],
    "1336_down": [],
    "845_up": [],
    "845_down": [],
    "134_up": [],
    "134_down": [],
    "5003_up": [],
    "5003_down": [],
    "8001_up": [],
    "8001_down": [],
    "889_up": [],
    "889_down": [],
    "228_up": [],
    "228_down": [],
    "6088_up": [],
    "6088_down": [],
    "1855_up": [],
    "1855_down": [],
    "265_up": [],
    "265_down": [],
    "891_up": [],
    "891_down": [],
    "102_up": [],
    "102_down": [],
    "6106_up": [],
    "6106_down": [],
    "6148_up": [],
    "6148_down": [],
    "6288_up": [],
    "6288_down": [],
    "5021_up": [],
    "5021_down": [],
    "3341_up": [],
    "3341_down": [],
    "6020_up": [],
    "6020_down": [],
    "1322_up": [],
    "1322_down": [],
    "5020_up": [],
    "5020_down": [],
    "252_up": [],
    "252_down": [],
    "6322_up": [],
    "6322_down": [],
    "6084_up": [],
    "6084_down": [],
    "210_up": [],
    "210_down": [],
    "302_up": [],
    "302_down": [],
    "5063_up": [],
    "5063_down": [],
    "332_up": [],
    "332_down": [],
    "1237_up": [],
    "1237_down": [],
    "115_up": [],
    "115_down": [],
    "836_up": [],
    "836_down": [],
    "89_up": [],
    "89_down": [],
    "629_up": [],
    "629_down": [],
    "1345_up": [],
    "1345_down": [],
    "6253_up": [],
    "6253_down": [],
    "241Q_up": [],
    "241Q_down": [],
    "542_up": [],
    "542_down": [],
    "B2_up": [],
    "B2_down": [],
    "233_up": [],
    "233_down": [],
    "817_up": [],
    "817_down": [],
    "2107_up": [],
    "2107_down": [],
    "2853_up": [],
    "2853_down": [],
    "6042_up": [],
    "6042_down": [],
    "1302_up": [],
    "1302_down": [],
    "2308_up": [],
    "2308_down": [],
    "555_up": [],
    "555_down": [],
    "35_up": [],
    "35_down": [],
    "5029_up": [],
    "5029_down": [],
    "5025_up": [],
    "5025_down": [],
    "5069_up": [],
    "5069_down": [],
    "722_up": [],
    "722_down": [],
    "6239_up": [],
    "6239_down": [],
    "162_up": [],
    "162_down": [],
    "2240_up": [],
    "2240_down": [],
    "2340_up": [],
    "2340_down": [],
    "5005_up": [],
    "5005_down": [],
    "11_up": [],
    "11_down": [],
    "6171_up": [],
    "6171_down": [],
    "3218_up": [],
    "3218_down": [],
    "170_up": [],
    "170_down": [],
    "251_up": [],
    "251_down": [],
    "267_up": [],
    "267_down": [],
    "211_up": [],
    "211_down": [],
    "50_up": [],
    "50_down": [],
    "6041_up": [],
    "6041_down": [],
    "6147_up": [],
    "6147_down": [],
    "861_up": [],
    "861_down": [],
    "5016_up": [],
    "5016_down": [],
    "256_up": [],
    "256_down": [],
    "310_up": [],
    "310_down": [],
    "5046_up": [],
    "5046_down": [],
    "6210_up": [],
    "6210_down": [],
    "6006_up": [],
    "6006_down": [],
    "18_up": [],
    "18_down": [],
    "804_up": [],
    "804_down": [],
    "6252_up": [],
    "6252_down": [],
    "26_up": [],
    "26_down": [],
    "6167_up": [],
    "6167_down": [],
    "131_up": [],
    "131_down": [],
    "578_up": [],
    "578_down": [],
    "6140_up": [],
    "6140_down": [],
    "238Q_up": [],
    "238Q_down": [],
    "221_up": [],
    "221_down": [],
    "315_up": [],
    "315_down": [],
    "1672_up": [],
    "1672_down": [],
    "1824_up": [],
    "1824_down": [],
    "5009_up": [],
    "5009_down": [],
    "560_up": [],
    "560_down": [],
    "6174_up": [],
    "6174_down": [],
    "1577_up": [],
    "1577_down": [],
    "577_up": [],
    "577_down": [],
    "6110_up": [],
    "6110_down": [],
    "6194_up": [],
    "6194_down": [],
    "528_up": [],
    "528_down": [],
    "848_up": [],
    "848_down": [],
    "639_up": [],
    "639_down": [],
    "702_up": [],
    "702_down": [],
    "313_up": [],
    "313_down": [],
    "605_up": [],
    "605_down": [],
    "6320_up": [],
    "6320_down": [],
    "231_up": [],
    "231_down": [],
    "828_up": [],
    "828_down": [],
    "2672_up": [],
    "2672_down": [],
    "6028_up": [],
    "6028_down": [],
    "20_up": [],
    "20_down": [],
    "628_up": [],
    "628_down": [],
    "501_up": [],
    "501_down": [],
    "637_up": [],
    "637_down": [],
    "580_up": [],
    "580_down": [],
    "5038_up": [],
    "5038_down": [],
    "121_up": [],
    "121_down": [],
    "516_up": [],
    "516_down": [],
    "864_up": [],
    "864_down": [],
    "2128_up": [],
    "2128_down": [],
    "1510_up": [],
    "1510_down": [],
    "158_up": [],
    "158_down": [],
    "809_up": [],
    "809_down": [],
    "6178_up": [],
    "6178_down": [],
    "559_up": [],
    "559_down": [],
    "139_up": [],
    "139_down": [],
    "203_up": [],
    "203_down": [],
    "323_up": [],
    "323_down": [],
    "512_up": [],
    "512_down": [],
    "10826_up": [],
    "10826_down": [],
    "6259_up": [],
    "6259_down": [],
    "146_up": [],
    "146_down": [],
    "344_up": [],
    "344_down": [],
    "483_up": [],
    "483_down": [],
    "727_up": [],
    "727_down": [],
    "2343_up": [],
    "2343_down": [],
    "16_up": [],
    "16_down": [],
    "6192_up": [],
    "6192_down": [],
    "259_up": [],
    "259_down": [],
    "535_up": [],
    "535_down": [],
    "234_up": [],
    "234_down": [],
    "1530_up": [],
    "1530_down": [],
    "169_up": [],
    "169_down": [],
    "6175_up": [],
    "6175_down": [],
    "863_up": [],
    "863_down": [],
    "106_up": [],
    "106_down": [],
    "730_up": [],
    "730_down": [],
    "881_up": [],
    "881_down": [],
    "1532_up": [],
    "1532_down": [],
    "6029_up": [],
    "6029_down": [],
    "1332_up": [],
    "1332_down": [],
    "6296_up": [],
    "6296_down": [],
    "133_up": [],
    "133_down": [],
    "108_up": [],
    "108_down": [],
    "6166_up": [],
    "6166_down": [],
    "508_up": [],
    "508_down": [],
    "666_up": [],
    "666_down": [],
    "6143_up": [],
    "6143_down": [],
    "6001_up": [],
    "6001_down": [],
    "726_up": [],
    "726_down": [],
    "5049_up": [],
    "5049_down": [],
    "161_up": [],
    "161_down": [],
    "823_up": [],
    "823_down": [],
    "2131_up": [],
    "2131_down": [],
    "5032_up": [],
    "5032_down": [],
    "103_up": [],
    "103_down": [],
    "5040_up": [],
    "5040_down": [],
    "2237_up": [],
    "2237_down": [],
    "5039_up": [],
    "5039_down": [],
    "6285_up": [],
    "6285_down": [],
    "5058_up": [],
    "5058_down": [],
    "224_up": [],
    "224_down": [],
    "216_up": [],
    "216_down": [],
    "6168_up": [],
    "6168_down": [],
    "1214_up": [],
    "1214_down": [],
    "1873_up": [],
    "1873_down": [],
    "129_up": [],
    "129_down": [],
    "509_up": [],
    "509_down": [],
    "551_up": [],
    "551_down": [],
    "317_up": [],
    "317_down": [],
    "503_up": [],
    "503_down": [],
    "6012_up": [],
    "6012_down": [],
    "6157_up": [],
    "6157_down": [],
    "526_up": [],
    "526_down": [],
    "2342_up": [],
    "2342_down": [],
    "6013_up": [],
    "6013_down": [],
    "142_up": [],
    "142_down": [],
    "522_up": [],
    "522_down": [],
    "556_up": [],
    "556_down": [],
    "829_up": [],
    "829_down": [],
    "879_up": [],
    "879_down": [],
    "6093_up": [],
    "6093_down": [],
    "6137_up": [],
    "6137_down": [],
    "6048_up": [],
    "6048_down": [],
    "2_up": [],
    "2_down": [],
    "527_up": [],
    "527_down": [],
    "719_up": [],
    "719_down": [],
    "718_up": [],
    "718_down": [],
    "261_up": [],
    "261_down": [],
    "5047_up": [],
    "5047_down": [],
    "6235_up": [],
    "6235_down": [],
    "635_up": [],
    "635_down": [],
    "840_up": [],
    "840_down": [],
    "838_up": [],
    "838_down": [],
    "B1_up": [],
    "B1_down": [],
    "1127_up": [],
    "1127_down": [],
    "6264_up": [],
    "6264_down": [],
    "204_up": [],
    "204_down": [],
    "830_up": [],
    "830_down": [],
    "214Y_up": [],
    "214Y_down": [],
    "558_up": [],
    "558_down": [],
    "1335_up": [],
    "1335_down": [],
    "5019_up": [],
    "5019_down": [],
    "5059_up": [],
    "5059_down": [],
    "732_up": [],
    "732_down": [],
    "567_up": [],
    "567_down": [],
    "1850_up": [],
    "1850_down": [],
    "150_up": [],
    "150_down": [],
    "212_up": [],
    "212_down": [],
    "255_up": [],
    "255_down": [],
    "6127_up": [],
    "6127_down": [],
    "5017_up": [],
    "5017_down": [],
    "3128_up": [],
    "3128_down": [],
    "2116_up": [],
    "2116_down": [],
    "6176_up": [],
    "6176_down": [],
    "258_up": [],
    "258_down": [],
    "2316_up": [],
    "2316_down": [],
    "540_up": [],
    "540_down": [],
    "707_up": [],
    "707_down": [],
    "235_up": [],
    "235_down": [],
    "105_up": [],
    "105_down": [],
    "211Q_up": [],
    "211Q_down": [],
    "8101_up": [],
    "8101_down": [],
    "1116_up": [],
    "1116_down": [],
    "1518_up": [],
    "1518_down": [],
    "606_up": [],
    "606_down": [],
    "32_up": [],
    "32_down": [],
    "6222_up": [],
    "6222_down": [],
    "15032_up": [],
    "15032_down": [],
    "176_up": [],
    "176_down": [],
    "6240_up": [],
    "6240_down": [],
    "6223_up": [],
    "6223_down": [],
    "841_up": [],
    "841_down": [],
    "18Q_up": [],
    "18Q_down": [],
    "5051_up": [],
    "5051_down": [],
    "220_up": [],
    "220_down": [],
    "2503_up": [],
    "2503_down": [],
    "208_up": [],
    "208_down": [],
    "8002_up": [],
    "8002_down": [],
    "6102_up": [],
    "6102_down": [],
    "180_up": [],
    "180_down": [],
    "6114_up": [],
    "6114_down": [],
    "28_up": [],
    "28_down": [],
    "6321_up": [],
    "6321_down": [],
    "166_up": [],
    "166_down": [],
    "37_up": [],
    "37_down": [],
    "630_up": [],
    "630_down": [],
    "8009_up": [],
    "8009_down": [],
    "1337_up": [],
    "1337_down": [],
    "6190_up": [],
    "6190_down": [],
    "513_up": [],
    "513_down": [],
    "320_up": [],
    "320_down": [],
    "5057_up": [],
    "5057_down": [],
    "6118_up": [],
    "6118_down": [],
    "618_up": [],
    "618_down": [],
    "1342_up": [],
    "1342_down": [],
    "846_up": [],
    "846_down": [],
    "6209_up": [],
    "6209_down": [],
    "1350_up": [],
    "1350_down": [],
    "543_up": [],
    "543_down": [],
    "6141_up": [],
    "6141_down": [],
    "137_up": [],
    "137_down": [],
    "6212_up": [],
    "6212_down": [],
    "801_up": [],
    "801_down": [],
    "850_up": [],
    "850_down": [],
    "805_up": [],
    "805_down": [],
    "6268_up": [],
    "6268_down": [],
    "6256_up": [],
    "6256_down": [],
    "123_up": [],
    "123_down": [],
    "5018_up": [],
    "5018_down": [],
    "553_up": [],
    "553_down": [],
    "6022_up": [],
    "6022_down": [],
    "3237_up": [],
    "3237_down": [],
    "205_up": [],
    "205_down": [],
    "309_up": [],
    "309_down": [],
    "5043_up": [],
    "5043_down": [],
    "6184_up": [],
    "6184_down": [],
    "10527_up": [],
    "10527_down": [],
    "1826_up": [],
    "1826_down": [],
    "6215_up": [],
    "6215_down": [],
    "207_up": [],
    "207_down": [],
    "127_up": [],
    "127_down": [],
    "876_up": [],
    "876_down": [],
    "631_up": [],
    "631_down": [],
    "214_up": [],
    "214_down": [],
    "611_up": [],
    "611_down": [],
    "303_up": [],
    "303_down": [],
    "858_up": [],
    "858_down": [],
    "5052_up": [],
    "5052_down": [],
    "5065_up": [],
    "5065_down": [],
    "119_up": [],
    "119_down": [],
    "855_up": [],
    "855_down": [],
    "337_up": [],
    "337_down": [],
    "101_up": [],
    "101_down": [],
    "269_up": [],
    "269_down": [],
    "6173_up": [],
    "6173_down": [],
    "217_up": [],
    "217_down": [],
    "835_up": [],
    "835_down": [],
    "5015_up": [],
    "5015_down": [],
    "2344_up": [],
    "2344_down": [],
    "336_up": [],
    "336_down": [],
    "2346_up": [],
    "2346_down": [],
    "38_up": [],
    "38_down": [],
    "607_up": [],
    "607_down": [],
    "6015_up": [],
    "6015_down": [],
    "243_up": [],
    "243_down": [],
    "132_up": [],
    "132_down": [],
    "715_up": [],
    "715_down": [],
    "421_up": [],
    "421_down": [],
    "6161_up": [],
    "6161_down": [],
    "515_up": [],
    "515_down": [],
    "1346_up": [],
    "1346_down": [],
    "321_up": [],
    "321_down": [],
    "887_up": [],
    "887_down": [],
    "871_up": [],
    "871_down": [],
    "6185_up": [],
    "6185_down": [],
    "K252_up": [],
    "K252_down": [],
    "561_up": [],
    "561_down": [],
    "3336_up": [],
    "3336_down": [],
    "6224_up": [],
    "6224_down": [],
    "834_up": [],
    "834_down": [],
    "6149_up": [],
    "6149_down": [],
    "168_up": [],
    "168_down": [],
    "6062_up": [],
    "6062_down": [],
    "6_up": [],
    "6_down": [],
    "586_up": [],
    "586_down": [],
    "5076_up": [],
    "5076_down": [],
    "484_up": [],
    "484_down": [],
    "135_up": [],
    "135_down": [],
    "6179_up": [],
    "6179_down": [],
    "520_up": [],
    "520_down": [],
    "1333_up": [],
    "1333_down": [],
    "5041_up": [],
    "5041_down": [],
    "6070_up": [],
    "6070_down": [],
    "6262_up": [],
    "6262_down": [],
    "156_up": [],
    "156_down": [],
    "482_up": [],
    "482_down": [],
    "6095_up": [],
    "6095_down": [],
    "248_up": [],
    "248_down": [],
    "305_up": [],
    "305_down": [],
    "3143_up": [],
    "3143_down": [],
    "510_up": [],
    "510_down": [],
    "672_up": [],
    "672_down": [],
    "826_up": [],
    "826_down": [],
    "6263_up": [],
    "6263_down": [],
    "5066_up": [],
    "5066_down": [],
    "301_up": [],
    "301_down": [],
    "5010_up": [],
    "5010_down": [],
    "609_up": [],
    "609_down": [],
    "343_up": [],
    "343_down": [],
    "501Q_up": [],
    "501Q_down": [],
    "151_up": [],
    "151_down": [],
    "886_up": [],
    "886_down": [],
    "5062_up": [],
    "5062_down": [],
    "885_up": [],
    "885_down": [],
    "136_up": [],
    "136_down": [],
    "15020_up": [],
    "15020_down": [],
    "1628_up": [],
    "1628_down": [],
    "585_up": [],
    "585_down": [],
    "6170_up": [],
    "6170_down": [],
    "1344_up": [],
    "1344_down": [],
    "263_up": [],
    "263_down": [],
    "6026_up": [],
    "6026_down": [],
    "6129_up": [],
    "6129_down": [],
    "5077_up": [],
    "5077_down": [],
    "816_up": [],
    "816_down": [],
    "33_up": [],
    "33_down": [],
    "671_up": [],
    "671_down": [],
    "2336_up": [],
    "2336_down": [],
    "6183_up": [],
    "6183_down": [],
    "257_up": [],
    "257_down": [],
    "227_up": [],
    "227_down": [],
    "163_up": [],
    "163_down": [],
    "126_up": [],
    "126_down": [],
    "2825_up": [],
    "2825_down": [],
    "832_up": [],
    "832_down": [],
    "178_up": [],
    "178_down": [],
    "882_up": [],
    "882_down": [],
    "6025_up": [],
    "6025_down": [],
    "5055_up": [],
    "5055_down": [],
    "7_up": [],
    "7_down": [],
    "319_up": [],
    "319_down": [],
    "6282_up": [],
    "6282_down": [],
    "6032_up": [],
    "6032_down": [],
    "5012_up": [],
    "5012_down": [],
    "6286_up": [],
    "6286_down": [],
    "209_up": [],
    "209_down": [],
    "859_up": [],
    "859_down": [],
    "27_up": [],
    "27_down": [],
    "842_up": [],
    "842_down": [],
    "843_up": [],
    "843_down": [],
    "3308_up": [],
    "3308_down": [],
    "6236_up": [],
    "6236_down": [],
    "5035_up": [],
    "5035_down": [],
    "349_up": [],
    "349_down": [],
    "708_up": [],
    "708_down": [],
    "241_up": [],
    "241_down": [],
    "6094_up": [],
    "6094_down": [],
    "614_up": [],
    "614_down": [],
    "6134_up": [],
    "6134_down": [],
    "3_up": [],
    "3_down": [],
    "5028_up": [],
    "5028_down": [],
    "237_up": [],
    "237_down": [],
    "530_up": [],
    "530_down": [],
    "487_up": [],
    "487_down": [],
    "1315_up": [],
    "1315_down": [],
    "6265_up": [],
    "6265_down": [],
    "1212_up": [],
    "1212_down": [],
    "5050_up": [],
    "5050_down": [],
    "2334_up": [],
    "2334_down": [],
    "350_up": [],
    "350_down": [],
    "6312_up": [],
    "6312_down": [],
    "262_up": [],
    "262_down": [],
    "721_up": [],
    "721_down": [],
    "587_up": [],
    "587_down": [],
    "266_up": [],
    "266_down": [],
    "617_up": [],
    "617_down": [],
    "619_up": [],
    "619_down": [],
    "6040_up": [],
    "6040_down": [],
    "6097_up": [],
    "6097_down": [],
    "615_up": [],
    "615_down": [],
    "608_up": [],
    "608_down": [],
    "181_up": [],
    "181_down": [],
    "6295_up": [],
    "6295_down": [],
    "3116_up": [],
    "3116_down": [],
    "822_up": [],
    "822_down": [],
    "713_up": [],
    "713_down": [],
    "5073_up": [],
    "5073_down": [],
    "9_up": [],
    "9_down": [],
    "6061_up": [],
    "6061_down": [],
    "340_up": [],
    "340_down": [],
    "6261_up": [],
    "6261_down": [],
    "230_up": [],
    "230_down": [],
    "306_up": [],
    "306_down": [],
    "5045_up": [],
    "5045_down": [],
    "1343_up": [],
    "1343_down": [],
    "5022_up": [],
    "5022_down": [],
    "5068_up": [],
    "5068_down": [],
    "883_up": [],
    "883_down": [],
    "6283_up": [],
    "6283_down": [],
    "5075_up": [],
    "5075_down": [],
    "167_up": [],
    "167_down": [],
    "2345_up": [],
    "2345_down": [],
    "342_up": [],
    "342_down": [],
    "22_up": [],
    "22_down": [],
    "6254_up": [],
    "6254_down": [],
    "10_up": [],
    "10_down": [],
    "130_up": [],
    "130_down": [],
    "849_up": [],
    "849_down": [],
    "1319_up": [],
    "1319_down": [],
    "6132_up": [],
    "6132_down": [],
    "240_up": [],
    "240_down": [],
    "1349_up": [],
    "1349_down": [],
    "52_up": [],
    "52_down": [],
    "517_up": [],
    "517_down": [],
    "875_up": [],
    "875_down": [],
    "245_up": [],
    "245_down": [],
    "3518_up": [],
    "3518_down": [],
    "486_up": [],
    "486_down": [],
    "5037_up": [],
    "5037_down": [],
    "6181_up": [],
    "6181_down": [],
    "485_up": [],
    "485_down": [],
    "6248_up": [],
    "6248_down": [],
    "5061_up": [],
    "5061_down": [],
    "225_up": [],
    "225_down": [],
    "311_up": [],
    "311_down": [],
    "1503_up": [],
    "1503_down": [],
    "5_up": [],
    "5_down": [],
    "316_up": [],
    "316_down": [],
    "806_up": [],
    "806_down": [],
    "5001_up": [],
    "5001_down": [],
    "6241_up": [],
    "6241_down": [],
    "6151_up": [],
    "6151_down": [],
    "6255_up": [],
    "6255_down": [],
    "820_up": [],
    "820_down": [],
    "481_up": [],
    "481_down": [],
    "1306_up": [],
    "1306_down": [],
    "6136_up": [],
    "6136_down": [],
    "232_up": [],
    "232_down": [],
    "346_up": [],
    "346_down": [],
    "5056_up": [],
    "5056_down": [],
    "6228_up": [],
    "6228_down": [],
    "238_up": [],
    "238_down": [],
    "870_up": [],
    "870_down": [],
    "5031_up": [],
    "5031_down": [],
    "853_up": [],
    "853_down": [],
    "880_up": [],
    "880_down": [],
    "247_up": [],
    "247_down": [],
    "111_up": [],
    "111_down": [],
    "562_up": [],
    "562_down": [],
    "5006_up": [],
    "5006_down": [],
    "877_up": [],
    "877_down": [],
    "345_up": [],
    "345_down": [],
    "335_up": [],
    "335_down": [],
    "6046_up": [],
    "6046_down": [],
    "878_up": [],
    "878_down": [],
    "1853_up": [],
    "1853_down": [],
    "575_up": [],
    "575_down": [],
    "6299_up": [],
    "6299_down": [],
    "113_up": [],
    "113_down": [],
    "12_up": [],
    "12_down": [],
    "6193_up": [],
    "6193_down": [],
    "5023_up": [],
    "5023_down": [],
    "51_up": [],
    "51_down": [],
    "215_up": [],
    "215_down": [],
    "341_up": [],
    "341_down": [],
    "6003_up": [],
    "6003_down": [],
    "17_up": [],
    "17_down": [],
    "105Q_up": [],
    "105Q_down": [],
    "5044_up": [],
    "5044_down": [],
    "5004_up": [],
    "5004_down": [],
    "6315_up": [],
    "6315_down": [],
    "118_up": [],
    "118_down": [],
    "4_up": [],
    "4_down": [],
    "206_up": [],
    "206_down": [],
    "21_up": [],
    "21_down": [],
    "5008_up": [],
    "5008_down": [],
    "847_up": [],
    "847_down": [],
    "5042_up": [],
    "5042_down": [],
    "1308_up": [],
    "1308_down": [],
    "107_up": [],
    "107_down": [],
    "1039_up": [],
    "1039_down": [],
    "6226_up": [],
    "6226_down": [],
    "725_up": [],
    "725_down": [],
    "31_up": [],
    "31_down": [],
    "39_up": [],
    "39_down": [],
    "6317_up": [],
    "6317_down": [],
    "557_up": [],
    "557_down": [],
    "5030_up": [],
    "5030_down": [],
    "171_up": [],
    "171_down": [],
    "125_up": [],
    "125_down": [],
    "531_up": [],
    "531_down": [],
    "19_up": [],
    "19_down": [],
    "6172_up": [],
    "6172_down": [],
    "6227_up": [],
    "6227_down": [],
    "2143_up": [],
    "2143_down": [],
    "6038_up": [],
    "6038_down": [],
    "6014_up": [],
    "6014_down": [],
    "308_up": [],
    "308_down": [],
    "5048_up": [],
    "5048_down": [],
    "825_up": [],
    "825_down": [],
    "330_up": [],
    "330_down": [],
    "159_up": [],
    "159_down": [],
    "3338_up": [],
    "3338_down": [],
    "29_up": [],
    "29_down": []
}